setup.py
django_yubikey_admin/__init__.py
django_yubikey_admin/admin.py
django_yubikey_admin/apps.py
django_yubikey_admin/auth_backends.py
django_yubikey_admin/forms.py
django_yubikey_admin/models.py
django_yubikey_admin.egg-info/PKG-INFO
django_yubikey_admin.egg-info/SOURCES.txt
django_yubikey_admin.egg-info/dependency_links.txt
django_yubikey_admin.egg-info/not-zip-safe
django_yubikey_admin.egg-info/requires.txt
django_yubikey_admin.egg-info/top_level.txt
django_yubikey_admin/migrations/0001_initial.py
django_yubikey_admin/migrations/__init__.py