Metadata-Version: 1.1
Name: django-yubikey-admin
Version: 0.5.4
Summary: Yubikey Support for the Django Admin.
Home-page: https://github.com/LyricalSecurity/django-yubikey-admin/
Author: Chayim Kirshen
Author-email: chayim@lyricalsecurity.com
License: UNKNOWN
Platform: UNKNOWN
Classifier: Development Status :: 5 - Production/Stable
Classifier: Environment :: Web Environment
Classifier: Intended Audience :: Developers
Classifier: License :: OSI Approved :: MIT License
Classifier: Operating System :: OS Independent
Classifier: Programming Language :: Python
Classifier: Programming Language :: Python :: 2.7
Classifier: Programming Language :: Python :: 3.4
Classifier: Framework :: Django
